{
    "image_id": "03b764f7-d39580d9-90feb2a7-fa490ab6-0e5fc617",
    "viewpoint": "AP",
    "patient_id": 18880255,
    "study_id": 58123377,
    "gender": "F",
    "age_decile": "20-30",
    "reason_for_exam": "Altered mental status and leukocytosis.",
    "StudyOrder": 2,
    "StudyDateTime": "2184-10-23 22:55:09 UTC",
    "objects": [
        {
            "object_id": "03b764f7-d39580d9-90feb2a7-fa490ab6-0e5fc617_right lung",
            "x1": 34,
            "y1": 41,
            "x2": 103,
            "y2": 192,
            "width": 69,
            "height": 151,
            "bbox_name": "right lung",
            "synsets": [
                "C0225706"
            ],
            "name": "Right lung",
            "original_x1": 204,
            "original_y1": 559,
            "original_x2": 1146,
            "original_y2": 2619,
            "original_width": 942,
            "original_height": 2060
        },
        {
            "object_id": "03b764f7-d39580d9-90feb2a7-fa490ab6-0e5fc617_right upper lung zone",
            "x1": 47,
            "y1": 46,
            "x2": 103,
            "y2": 93,
            "width": 56,
            "height": 47,
            "bbox_name": "right upper lung zone",
            "synsets": [
                "C0934570"
            ],
            "name": "Right upper lung zone",
            "original_x1": 382,
            "original_y1": 627,
            "original_x2": 1146,
            "original_y2": 1268,
            "original_width": 764,
            "original_height": 641
        },
        {
            "object_id": "03b764f7-d39580d9-90feb2a7-fa490ab6-0e5fc617_right mid lung zone",
            "x1": 41,
            "y1": 93,
            "x2": 100,
            "y2": 129,
            "width": 59,
            "height": 36,
            "bbox_name": "right mid lung zone",
            "synsets": [
                "CL380307"
            ],
            "name": "Right mid lung zone",
            "original_x1": 300,
            "original_y1": 1268,
            "original_x2": 1105,
            "original_y2": 1759,
            "original_width": 805,
            "original_height": 491
        },
        {
            "object_id": "03b764f7-d39580d9-90feb2a7-fa490ab6-0e5fc617_right lower lung zone",
            "x1": 34,
            "y1": 129,
            "x2": 97,
            "y2": 192,
            "width": 63,
            "height": 63,
            "bbox_name": "right lower lung zone",
            "synsets": [
                "C0929214"
            ],
            "name": "Right lower lung zone",
            "original_x1": 204,
            "original_y1": 1759,
            "original_x2": 1064,
            "original_y2": 2619,
            "original_width": 860,
            "original_height": 860
        },
        {
            "object_id": "03b764f7-d39580d9-90feb2a7-fa490ab6-0e5fc617_right hilar structures",
            "x1": 70,
            "y1": 85,
            "x2": 101,
            "y2": 136,
            "width": 31,
            "height": 51,
            "bbox_name": "right hilar structures",
            "synsets": [
                "C1708369"
            ],
            "name": "Hilar Area of the Right Lung",
            "original_x1": 695,
            "original_y1": 1159,
            "original_x2": 1118,
            "original_y2": 1855,
            "original_width": 423,
            "original_height": 696
        },
        {
            "object_id": "03b764f7-d39580d9-90feb2a7-fa490ab6-0e5fc617_right apical zone",
            "x1": 53,
            "y1": 41,
            "x2": 103,
            "y2": 71,
            "width": 50,
            "height": 30,
            "bbox_name": "right apical zone",
            "synsets": [
                "C0929167"
            ],
            "name": "Apical zone of right lung",
            "original_x1": 463,
            "original_y1": 559,
            "original_x2": 1146,
            "original_y2": 968,
            "original_width": 683,
            "original_height": 409
        },
        {
            "object_id": "03b764f7-d39580d9-90feb2a7-fa490ab6-0e5fc617_right costophrenic angle",
            "x1": 24,
            "y1": 177,
            "x2": 44,
            "y2": 197,
            "width": 20,
            "height": 20,
            "bbox_name": "right costophrenic angle",
            "synsets": [
                "CL380392",
                "C0504099"
            ],
            "name": "right costophrenic sulcus;;Right costodiaphragmatic recess",
            "original_x1": 68,
            "original_y1": 2414,
            "original_x2": 341,
            "original_y2": 2687,
            "original_width": 273,
            "original_height": 273
        },
        {
            "object_id": "03b764f7-d39580d9-90feb2a7-fa490ab6-0e5fc617_right cardiophrenic angle",
            "x1": 85,
            "y1": 147,
            "x2": 91,
            "y2": 166,
            "width": 6,
            "height": 19,
            "bbox_name": "right cardiophrenic angle",
            "synsets": [
                "CL380389"
            ],
            "name": "right cardiophrenic sulcus",
            "original_x1": 900,
            "original_y1": 2005,
            "original_x2": 982,
            "original_y2": 2264,
            "original_width": 82,
            "original_height": 259
        },
        {
            "object_id": "03b764f7-d39580d9-90feb2a7-fa490ab6-0e5fc617_right hemidiaphragm",
            "x1": 34,
            "y1": 150,
            "x2": 105,
            "y2": 192,
            "width": 71,
            "height": 42,
            "bbox_name": "right hemidiaphragm",
            "synsets": [
                "C0929193"
            ],
            "name": "Right hemidiaphragm",
            "original_x1": 204,
            "original_y1": 2046,
            "original_x2": 1173,
            "original_y2": 2619,
            "original_width": 969,
            "original_height": 573
        },
        {
            "object_id": "03b764f7-d39580d9-90feb2a7-fa490ab6-0e5fc617_left lung",
            "x1": 116,
            "y1": 37,
            "x2": 183,
            "y2": 190,
            "width": 67,
            "height": 153,
            "bbox_name": "left lung",
            "synsets": [
                "C0225730"
            ],
            "name": "Left lung",
            "original_x1": 1323,
            "original_y1": 504,
            "original_x2": 2237,
            "original_y2": 2592,
            "original_width": 914,
            "original_height": 2088
        },
        {
            "object_id": "03b764f7-d39580d9-90feb2a7-fa490ab6-0e5fc617_left upper lung zone",
            "x1": 116,
            "y1": 42,
            "x2": 174,
            "y2": 93,
            "width": 58,
            "height": 51,
            "bbox_name": "left upper lung zone",
            "synsets": [
                "C0929215"
            ],
            "name": "Left upper lung zone",
            "original_x1": 1323,
            "original_y1": 573,
            "original_x2": 2114,
            "original_y2": 1268,
            "original_width": 791,
            "original_height": 695
        },
        {
            "object_id": "03b764f7-d39580d9-90feb2a7-fa490ab6-0e5fc617_left mid lung zone",
            "x1": 117,
            "y1": 93,
            "x2": 178,
            "y2": 128,
            "width": 61,
            "height": 35,
            "bbox_name": "left mid lung zone",
            "synsets": [
                "CL380306"
            ],
            "name": "Left mid lung zone",
            "original_x1": 1337,
            "original_y1": 1268,
            "original_x2": 2169,
            "original_y2": 1746,
            "original_width": 832,
            "original_height": 478
        },
        {
            "object_id": "03b764f7-d39580d9-90feb2a7-fa490ab6-0e5fc617_left lower lung zone",
            "x1": 116,
            "y1": 128,
            "x2": 183,
            "y2": 190,
            "width": 67,
            "height": 62,
            "bbox_name": "left lower lung zone",
            "synsets": [
                "C0934571"
            ],
            "name": "Left lower lung zone",
            "original_x1": 1323,
            "original_y1": 1746,
            "original_x2": 2237,
            "original_y2": 2592,
            "original_width": 914,
            "original_height": 846
        },
        {
            "object_id": "03b764f7-d39580d9-90feb2a7-fa490ab6-0e5fc617_left hilar structures",
            "x1": 116,
            "y1": 86,
            "x2": 147,
            "y2": 135,
            "width": 31,
            "height": 49,
            "bbox_name": "left hilar structures",
            "synsets": [
                "C1708367"
            ],
            "name": "Hilar Area of the Left Lung",
            "original_x1": 1323,
            "original_y1": 1173,
            "original_x2": 1746,
            "original_y2": 1841,
            "original_width": 423,
            "original_height": 668
        },
        {
            "object_id": "03b764f7-d39580d9-90feb2a7-fa490ab6-0e5fc617_left apical zone",
            "x1": 116,
            "y1": 37,
            "x2": 167,
            "y2": 71,
            "width": 51,
            "height": 34,
            "bbox_name": "left apical zone",
            "synsets": [
                "C0929168"
            ],
            "name": "Apical zone of left lung",
            "original_x1": 1323,
            "original_y1": 504,
            "original_x2": 2019,
            "original_y2": 968,
            "original_width": 696,
            "original_height": 464
        },
        {
            "object_id": "03b764f7-d39580d9-90feb2a7-fa490ab6-0e5fc617_left costophrenic angle",
            "x1": 173,
            "y1": 175,
            "x2": 193,
            "y2": 195,
            "width": 20,
            "height": 20,
            "bbox_name": "left costophrenic angle",
            "synsets": [
                "CL380391",
                "C0504100"
            ],
            "name": "left costophrenic sulcus;;Left costodiaphragmatic recess",
            "original_x1": 2101,
            "original_y1": 2387,
            "original_x2": 2373,
            "original_y2": 2660,
            "original_width": 272,
            "original_height": 273
        },
        {
            "object_id": "03b764f7-d39580d9-90feb2a7-fa490ab6-0e5fc617_left hemidiaphragm",
            "x1": 116,
            "y1": 157,
            "x2": 183,
            "y2": 190,
            "width": 67,
            "height": 33,
            "bbox_name": "left hemidiaphragm",
            "synsets": [
                "C0929194"
            ],
            "name": "Left hemidiaphragm",
            "original_x1": 1323,
            "original_y1": 2141,
            "original_x2": 2237,
            "original_y2": 2592,
            "original_width": 914,
            "original_height": 451
        },
        {
            "object_id": "03b764f7-d39580d9-90feb2a7-fa490ab6-0e5fc617_trachea",
            "x1": 89,
            "y1": 21,
            "x2": 120,
            "y2": 113,
            "width": 31,
            "height": 92,
            "bbox_name": "trachea",
            "synsets": [
                "C0040578&&C0024496"
            ],
            "name": "Trachea&&Main Bronchus",
            "original_x1": 955,
            "original_y1": 286,
            "original_x2": 1377,
            "original_y2": 1541,
            "original_width": 422,
            "original_height": 1255
        },
        {
            "object_id": "03b764f7-d39580d9-90feb2a7-fa490ab6-0e5fc617_spine",
            "x1": 84,
            "y1": 0,
            "x2": 118,
            "y2": 223,
            "width": 34,
            "height": 223,
            "bbox_name": "spine",
            "synsets": [
                "C0037949"
            ],
            "name": "Vertebral column",
            "original_x1": 886,
            "original_y1": 0,
            "original_x2": 1350,
            "original_y2": 3042,
            "original_width": 464,
            "original_height": 3042
        },
        {
            "object_id": "03b764f7-d39580d9-90feb2a7-fa490ab6-0e5fc617_right clavicle",
            "x1": 24,
            "y1": 40,
            "x2": 98,
            "y2": 71,
            "width": 74,
            "height": 31,
            "bbox_name": "right clavicle",
            "synsets": [
                "C0507156"
            ],
            "name": "Right clavicle",
            "original_x1": 68,
            "original_y1": 545,
            "original_x2": 1077,
            "original_y2": 968,
            "original_width": 1009,
            "original_height": 423
        },
        {
            "object_id": "03b764f7-d39580d9-90feb2a7-fa490ab6-0e5fc617_left clavicle",
            "x1": 117,
            "y1": 31,
            "x2": 185,
            "y2": 69,
            "width": 68,
            "height": 38,
            "bbox_name": "left clavicle",
            "synsets": [
                "C0507157"
            ],
            "name": "Left clavicle",
            "original_x1": 1337,
            "original_y1": 422,
            "original_x2": 2264,
            "original_y2": 941,
            "original_width": 927,
            "original_height": 519
        },
        {
            "object_id": "03b764f7-d39580d9-90feb2a7-fa490ab6-0e5fc617_aortic arch",
            "x1": 109,
            "y1": 77,
            "x2": 124,
            "y2": 93,
            "width": 15,
            "height": 16,
            "bbox_name": "aortic arch",
            "synsets": [
                "C0003489"
            ],
            "name": "Aortic arch structure",
            "original_x1": 1227,
            "original_y1": 1050,
            "original_x2": 1432,
            "original_y2": 1268,
            "original_width": 205,
            "original_height": 218
        },
        {
            "object_id": "03b764f7-d39580d9-90feb2a7-fa490ab6-0e5fc617_mediastinum",
            "x1": 88,
            "y1": 56,
            "x2": 155,
            "y2": 167,
            "width": 67,
            "height": 111,
            "bbox_name": "mediastinum",
            "synsets": [
                "C0025066"
            ],
            "name": "Mediastinum",
            "original_x1": 941,
            "original_y1": 764,
            "original_x2": 1855,
            "original_y2": 2278,
            "original_width": 914,
            "original_height": 1514
        },
        {
            "object_id": "03b764f7-d39580d9-90feb2a7-fa490ab6-0e5fc617_upper mediastinum",
            "x1": 93,
            "y1": 56,
            "x2": 130,
            "y2": 110,
            "width": 37,
            "height": 54,
            "bbox_name": "upper mediastinum",
            "synsets": [
                "C0230147"
            ],
            "name": "Superior mediastinum",
            "original_x1": 1009,
            "original_y1": 764,
            "original_x2": 1514,
            "original_y2": 1500,
            "original_width": 505,
            "original_height": 736
        },
        {
            "object_id": "03b764f7-d39580d9-90feb2a7-fa490ab6-0e5fc617_svc",
            "x1": 93,
            "y1": 77,
            "x2": 109,
            "y2": 110,
            "width": 16,
            "height": 33,
            "bbox_name": "svc",
            "synsets": [
                "C0042459"
            ],
            "name": "Superior vena cava structure",
            "original_x1": 1009,
            "original_y1": 1050,
            "original_x2": 1227,
            "original_y2": 1500,
            "original_width": 218,
            "original_height": 450
        },
        {
            "object_id": "03b764f7-d39580d9-90feb2a7-fa490ab6-0e5fc617_cardiac silhouette",
            "x1": 88,
            "y1": 111,
            "x2": 155,
            "y2": 167,
            "width": 67,
            "height": 56,
            "bbox_name": "cardiac silhouette",
            "synsets": [
                "C0507134",
                "C0018787"
            ],
            "name": "Cardiac shadow viewed radiologically;;Heart",
            "original_x1": 941,
            "original_y1": 1514,
            "original_x2": 1855,
            "original_y2": 2278,
            "original_width": 914,
            "original_height": 764
        },
        {
            "object_id": "03b764f7-d39580d9-90feb2a7-fa490ab6-0e5fc617_left cardiac silhouette",
            "x1": 101,
            "y1": 111,
            "x2": 155,
            "y2": 167,
            "width": 54,
            "height": 56,
            "bbox_name": "left cardiac silhouette",
            "synsets": [
                "C0225819"
            ],
            "name": "Structure of left margin of heart",
            "original_x1": 1118,
            "original_y1": 1514,
            "original_x2": 1855,
            "original_y2": 2278,
            "original_width": 737,
            "original_height": 764
        },
        {
            "object_id": "03b764f7-d39580d9-90feb2a7-fa490ab6-0e5fc617_right cardiac silhouette",
            "x1": 88,
            "y1": 111,
            "x2": 100,
            "y2": 158,
            "width": 12,
            "height": 47,
            "bbox_name": "right cardiac silhouette",
            "synsets": [
                "C0502335"
            ],
            "name": "Right border of heart viewed radiologically",
            "original_x1": 941,
            "original_y1": 1514,
            "original_x2": 1105,
            "original_y2": 2155,
            "original_width": 164,
            "original_height": 641
        },
        {
            "object_id": "03b764f7-d39580d9-90feb2a7-fa490ab6-0e5fc617_cavoatrial junction",
            "x1": 88,
            "y1": 111,
            "x2": 100,
            "y2": 126,
            "width": 12,
            "height": 15,
            "bbox_name": "cavoatrial junction",
            "synsets": [
                "CL493350"
            ],
            "name": "cavoatrial",
            "original_x1": 941,
            "original_y1": 1514,
            "original_x2": 1105,
            "original_y2": 1719,
            "original_width": 164,
            "original_height": 205
        },
        {
            "object_id": "03b764f7-d39580d9-90feb2a7-fa490ab6-0e5fc617_right atrium",
            "x1": 88,
            "y1": 126,
            "x2": 100,
            "y2": 158,
            "width": 12,
            "height": 32,
            "bbox_name": "right atrium",
            "synsets": [
                "C0225844"
            ],
            "name": "Right atrial structure",
            "original_x1": 941,
            "original_y1": 1719,
            "original_x2": 1105,
            "original_y2": 2155,
            "original_width": 164,
            "original_height": 436
        },
        {
            "object_id": "03b764f7-d39580d9-90feb2a7-fa490ab6-0e5fc617_descending aorta",
            "x1": 110,
            "y1": 88,
            "x2": 124,
            "y2": 128,
            "width": 14,
            "height": 40,
            "bbox_name": "descending aorta",
            "synsets": [
                "C0011666"
            ],
            "name": "Descending aorta",
            "original_x1": 1241,
            "original_y1": 1200,
            "original_x2": 1432,
            "original_y2": 1746,
            "original_width": 191,
            "original_height": 546
        },
        {
            "object_id": "03b764f7-d39580d9-90feb2a7-fa490ab6-0e5fc617_carina",
            "x1": 101,
            "y1": 89,
            "x2": 111,
            "y2": 99,
            "width": 10,
            "height": 10,
            "bbox_name": "carina",
            "synsets": [
                "C0225594"
            ],
            "name": "Structure of carina",
            "original_x1": 1118,
            "original_y1": 1214,
            "original_x2": 1255,
            "original_y2": 1350,
            "original_width": 137,
            "original_height": 136
        },
        {
            "object_id": "03b764f7-d39580d9-90feb2a7-fa490ab6-0e5fc617_left upper abdomen",
            "x1": 110,
            "y1": 162,
            "x2": 183,
            "y2": 223,
            "width": 73,
            "height": 61,
            "bbox_name": "left upper abdomen",
            "synsets": [
                "C0230179"
            ],
            "name": "Structure of left upper quadrant of abdomen",
            "original_x1": 1241,
            "original_y1": 2210,
            "original_x2": 2237,
            "original_y2": 3042,
            "original_width": 996,
            "original_height": 832
        },
        {
            "object_id": "03b764f7-d39580d9-90feb2a7-fa490ab6-0e5fc617_right upper abdomen",
            "x1": 34,
            "y1": 155,
            "x2": 110,
            "y2": 223,
            "width": 76,
            "height": 68,
            "bbox_name": "right upper abdomen",
            "synsets": [
                "C0230177"
            ],
            "name": "Structure of right upper quadrant of abdomen",
            "original_x1": 204,
            "original_y1": 2114,
            "original_x2": 1241,
            "original_y2": 3042,
            "original_width": 1037,
            "original_height": 928
        },
        {
            "object_id": "03b764f7-d39580d9-90feb2a7-fa490ab6-0e5fc617_abdomen",
            "x1": 34,
            "y1": 155,
            "x2": 183,
            "y2": 223,
            "width": 149,
            "height": 68,
            "bbox_name": "abdomen",
            "synsets": [
                "C0230168"
            ],
            "name": "Abdominal cavity",
            "original_x1": 204,
            "original_y1": 2114,
            "original_x2": 2237,
            "original_y2": 3042,
            "original_width": 2033,
            "original_height": 928
        },
        {
            "object_id": "03b764f7-d39580d9-90feb2a7-fa490ab6-0e5fc617_left cardiophrenic angle",
            "x1": 148,
            "y1": 150,
            "x2": 165,
            "y2": 167,
            "width": 17,
            "height": 17,
            "bbox_name": "left cardiophrenic angle",
            "synsets": [
                "CL380388"
            ],
            "name": "left cardiophrenic sulcus",
            "original_x1": 1759,
            "original_y1": 2046,
            "original_x2": 1991,
            "original_y2": 2278,
            "original_width": 232,
            "original_height": 232
        }
    ],
    "attributes": [
        {
            "right lung": true,
            "bbox_name": "right lung",
            "synsets": [
                "C0225706"
            ],
            "name": "Right lung",
            "attributes": [
                [
                    "anatomicalfinding|no|pleural effusion",
                    "anatomicalfinding|no|pneumothorax"
                ],
                [
                    "anatomicalfinding|no|lung opacity",
                    "nlp|yes|normal"
                ],
                [
                    "nlp|no|abnormal",
                    "nlp|yes|normal"
                ]
            ],
            "attributes_ids": [
                [
                    "CL545973;;C0032227",
                    "C1963215;;C0032326"
                ],
                [
                    "CL556823",
                    "C1550457"
                ],
                [
                    "C0205161",
                    "C1550457"
                ]
            ],
            "phrases": [
                "There is no\n pleural effusion or pneumothorax.",
                "The\n lungs appear clear.",
                "No evidence of acute cardiopulmonary disease."
            ],
            "phrase_IDs": [
                "58123377|7",
                "58123377|9",
                "58123377|12"
            ],
            "sections": [
                "finalreport",
                "finalreport",
                "finalreport"
            ],
            "comparison_cues": [
                [],
                [],
                []
            ],
            "temporal_cues": [
                [],
                [],
                [
                    "temporal|no|acute"
                ]
            ],
            "severity_cues": [
                [],
                [],
                []
            ],
            "texture_cues": [
                [],
                [],
                []
            ],
            "object_id": "03b764f7-d39580d9-90feb2a7-fa490ab6-0e5fc617_right lung"
        },
        {
            "right costophrenic angle": true,
            "bbox_name": "right costophrenic angle",
            "synsets": [
                "CL380392",
                "C0504099"
            ],
            "name": "right costophrenic sulcus;;Right costodiaphragmatic recess",
            "attributes": [
                [
                    "anatomicalfinding|no|pleural effusion"
                ]
            ],
            "attributes_ids": [
                [
                    "CL545973;;C0032227"
                ]
            ],
            "phrases": [
                "There is no\n pleural effusion or pneumothorax."
            ],
            "phrase_IDs": [
                "58123377|7"
            ],
            "sections": [
                "finalreport"
            ],
            "comparison_cues": [
                []
            ],
            "temporal_cues": [
                []
            ],
            "severity_cues": [
                []
            ],
            "texture_cues": [
                []
            ],
            "object_id": "03b764f7-d39580d9-90feb2a7-fa490ab6-0e5fc617_right costophrenic angle"
        },
        {
            "left lung": true,
            "bbox_name": "left lung",
            "synsets": [
                "C0225730"
            ],
            "name": "Left lung",
            "attributes": [
                [
                    "anatomicalfinding|no|pleural effusion",
                    "anatomicalfinding|no|pneumothorax"
                ],
                [
                    "anatomicalfinding|no|lung opacity"
                ],
                [
                    "anatomicalfinding|no|lung opacity",
                    "nlp|yes|normal"
                ],
                [
                    "nlp|no|abnormal",
                    "nlp|yes|normal"
                ]
            ],
            "attributes_ids": [
                [
                    "CL545973;;C0032227",
                    "C1963215;;C0032326"
                ],
                [
                    "CL556823"
                ],
                [
                    "CL556823",
                    "C1550457"
                ],
                [
                    "C0205161",
                    "C1550457"
                ]
            ],
            "phrases": [
                "There is no\n pleural effusion or pneumothorax.",
                "Left lower lobe opacity has resolved.",
                "The\n lungs appear clear.",
                "No evidence of acute cardiopulmonary disease."
            ],
            "phrase_IDs": [
                "58123377|7",
                "58123377|8",
                "58123377|9",
                "58123377|12"
            ],
            "sections": [
                "finalreport",
                "finalreport",
                "finalreport",
                "finalreport"
            ],
            "comparison_cues": [
                [],
                [
                    "comparison|yes|improved"
                ],
                [],
                []
            ],
            "temporal_cues": [
                [],
                [],
                [],
                [
                    "temporal|no|acute"
                ]
            ],
            "severity_cues": [
                [],
                [],
                [],
                []
            ],
            "texture_cues": [
                [],
                [
                    "texture|no|opacity"
                ],
                [],
                []
            ],
            "object_id": "03b764f7-d39580d9-90feb2a7-fa490ab6-0e5fc617_left lung"
        },
        {
            "left mid lung zone": true,
            "bbox_name": "left mid lung zone",
            "synsets": [
                "CL380306"
            ],
            "name": "Left mid lung zone",
            "attributes": [
                [
                    "anatomicalfinding|no|lung opacity"
                ]
            ],
            "attributes_ids": [
                [
                    "CL556823"
                ]
            ],
            "phrases": [
                "Left lower lobe opacity has resolved."
            ],
            "phrase_IDs": [
                "58123377|8"
            ],
            "sections": [
                "finalreport"
            ],
            "comparison_cues": [
                [
                    "comparison|yes|improved"
                ]
            ],
            "temporal_cues": [
                []
            ],
            "severity_cues": [
                []
            ],
            "texture_cues": [
                [
                    "texture|no|opacity"
                ]
            ],
            "object_id": "03b764f7-d39580d9-90feb2a7-fa490ab6-0e5fc617_left mid lung zone"
        },
        {
            "left lower lung zone": true,
            "bbox_name": "left lower lung zone",
            "synsets": [
                "C0934571"
            ],
            "name": "Left lower lung zone",
            "attributes": [
                [
                    "anatomicalfinding|no|lung opacity"
                ]
            ],
            "attributes_ids": [
                [
                    "CL556823"
                ]
            ],
            "phrases": [
                "Left lower lobe opacity has resolved."
            ],
            "phrase_IDs": [
                "58123377|8"
            ],
            "sections": [
                "finalreport"
            ],
            "comparison_cues": [
                [
                    "comparison|yes|improved"
                ]
            ],
            "temporal_cues": [
                []
            ],
            "severity_cues": [
                []
            ],
            "texture_cues": [
                [
                    "texture|no|opacity"
                ]
            ],
            "object_id": "03b764f7-d39580d9-90feb2a7-fa490ab6-0e5fc617_left lower lung zone"
        },
        {
            "left costophrenic angle": true,
            "bbox_name": "left costophrenic angle",
            "synsets": [
                "CL380391",
                "C0504100"
            ],
            "name": "left costophrenic sulcus;;Left costodiaphragmatic recess",
            "attributes": [
                [
                    "anatomicalfinding|no|pleural effusion"
                ]
            ],
            "attributes_ids": [
                [
                    "CL545973;;C0032227"
                ]
            ],
            "phrases": [
                "There is no\n pleural effusion or pneumothorax."
            ],
            "phrase_IDs": [
                "58123377|7"
            ],
            "sections": [
                "finalreport"
            ],
            "comparison_cues": [
                []
            ],
            "temporal_cues": [
                []
            ],
            "severity_cues": [
                []
            ],
            "texture_cues": [
                []
            ],
            "object_id": "03b764f7-d39580d9-90feb2a7-fa490ab6-0e5fc617_left costophrenic angle"
        },
        {
            "mediastinum": true,
            "bbox_name": "mediastinum",
            "synsets": [
                "C0025066"
            ],
            "name": "Mediastinum",
            "attributes": [
                [
                    "nlp|no|abnormal",
                    "nlp|yes|normal"
                ]
            ],
            "attributes_ids": [
                [
                    "C0205161",
                    "C1550457"
                ]
            ],
            "phrases": [
                "No evidence of acute cardiopulmonary disease."
            ],
            "phrase_IDs": [
                "58123377|12"
            ],
            "sections": [
                "finalreport"
            ],
            "comparison_cues": [
                []
            ],
            "temporal_cues": [
                [
                    "temporal|no|acute"
                ]
            ],
            "severity_cues": [
                []
            ],
            "texture_cues": [
                []
            ],
            "object_id": "03b764f7-d39580d9-90feb2a7-fa490ab6-0e5fc617_mediastinum"
        },
        {
            "cardiac silhouette": true,
            "bbox_name": "cardiac silhouette",
            "synsets": [
                "C0507134",
                "C0018787"
            ],
            "name": "Cardiac shadow viewed radiologically;;Heart",
            "attributes": [
                [
                    "nlp|no|abnormal",
                    "nlp|yes|normal"
                ]
            ],
            "attributes_ids": [
                [
                    "C0205161",
                    "C1550457"
                ]
            ],
            "phrases": [
                "No evidence of acute cardiopulmonary disease."
            ],
            "phrase_IDs": [
                "58123377|12"
            ],
            "sections": [
                "finalreport"
            ],
            "comparison_cues": [
                []
            ],
            "temporal_cues": [
                [
                    "temporal|no|acute"
                ]
            ],
            "severity_cues": [
                []
            ],
            "texture_cues": [
                []
            ],
            "object_id": "03b764f7-d39580d9-90feb2a7-fa490ab6-0e5fc617_cardiac silhouette"
        },
        {
            "spine": true,
            "bbox_name": "spine",
            "synsets": [
                "C0037949"
            ],
            "name": "Vertebral column",
            "attributes": [
                [
                    "anatomicalfinding|yes|scoliosis",
                    "nlp|yes|abnormal"
                ]
            ],
            "attributes_ids": [
                [
                    "C0036439",
                    "C0205161"
                ]
            ],
            "phrases": [
                "Mild reversed S-shaped curvature is again noted along the\n visualized thoracolumbar spine."
            ],
            "phrase_IDs": [
                "58123377|10"
            ],
            "sections": [
                "finalreport"
            ],
            "comparison_cues": [
                [
                    "comparison|yes|no change"
                ]
            ],
            "temporal_cues": [
                []
            ],
            "severity_cues": [
                [
                    "severity|yes|mild"
                ]
            ],
            "texture_cues": [
                []
            ],
            "object_id": "03b764f7-d39580d9-90feb2a7-fa490ab6-0e5fc617_spine"
        }
    ],
    "relationships": [
        {
            "relationship_id": "58123377|8_50657867_C0225730_03b764f7_b736c130",
            "predicate": "['Better']",
            "synsets": [
                "C0184511"
            ],
            "relationship_names": [
                "comparison|yes|improved"
            ],
            "relationship_contexts": [
                1.0
            ],
            "phrase": "Left lower lobe opacity has resolved.",
            "attributes": [
                "anatomicalfinding|no|lung opacity"
            ],
            "bbox_name": "left lung",
            "subject_id": "03b764f7-d39580d9-90feb2a7-fa490ab6-0e5fc617_left lung",
            "object_id": "b736c130-404b4310-cbee16f6-c4a70fd7-04571bfa_left lung"
        },
        {
            "relationship_id": "58123377|8_50657867_CL380306_03b764f7_b736c130",
            "predicate": "['Better']",
            "synsets": [
                "C0184511"
            ],
            "relationship_names": [
                "comparison|yes|improved"
            ],
            "relationship_contexts": [
                1.0
            ],
            "phrase": "Left lower lobe opacity has resolved.",
            "attributes": [
                "anatomicalfinding|no|lung opacity"
            ],
            "bbox_name": "left mid lung zone",
            "subject_id": "03b764f7-d39580d9-90feb2a7-fa490ab6-0e5fc617_left mid lung zone",
            "object_id": "b736c130-404b4310-cbee16f6-c4a70fd7-04571bfa_left mid lung zone"
        },
        {
            "relationship_id": "58123377|8_50657867_C0934571_03b764f7_b736c130",
            "predicate": "['Better']",
            "synsets": [
                "C0184511"
            ],
            "relationship_names": [
                "comparison|yes|improved"
            ],
            "relationship_contexts": [
                1.0
            ],
            "phrase": "Left lower lobe opacity has resolved.",
            "attributes": [
                "anatomicalfinding|no|lung opacity"
            ],
            "bbox_name": "left lower lung zone",
            "subject_id": "03b764f7-d39580d9-90feb2a7-fa490ab6-0e5fc617_left lower lung zone",
            "object_id": "b736c130-404b4310-cbee16f6-c4a70fd7-04571bfa_left lower lung zone"
        },
        {
            "relationship_id": "58123377|10_50657867_C0037949_03b764f7_b736c130",
            "predicate": "['No status change']",
            "synsets": [
                "C0442739"
            ],
            "relationship_names": [
                "comparison|yes|no change"
            ],
            "relationship_contexts": [
                1.0
            ],
            "phrase": "Mild reversed S-shaped curvature is again noted along the\n visualized thoracolumbar spine.",
            "attributes": [
                "anatomicalfinding|yes|scoliosis",
                "nlp|yes|abnormal"
            ],
            "bbox_name": "spine",
            "subject_id": "03b764f7-d39580d9-90feb2a7-fa490ab6-0e5fc617_spine",
            "object_id": "b736c130-404b4310-cbee16f6-c4a70fd7-04571bfa_spine"
        }
    ]
}